{
	"name": "default alpine theme",
	"colorSpaceName": "sRGB",
	"settings": [
		{
			"scope": [
				"comment.line.double-slash.todo.keyword.alpine"
			],
			"settings": {
				"foreground": "#AAAA00"
			}
		},
		{
			"scope": [
				"comment.line.double-slash.todo.alpine"
			],
			"settings": {
				"foreground": "#888888",
				"style": "italic"
			}
		},
		{
			"scope": [
				"comment.line.double-slash.alpine",
				"comment.line.double-slash"
			],
			"settings": {
				"foreground": "#6A9955"
			}
		},
		{
			"scope": [
				"string",
				"meta.embedded.assembly"
			],
			"settings": {
				"foreground": "#CE9178"
			}
		},
		{
			"scope": [
				"constant.numeric",
				"variable.other.enummember",
				"keyword.operator.plus.exponent",
				"keyword.operator.minus.exponent"
			],
			"settings": {
				"foreground": "#B5CEA8"
			}
		},
		{
			"scope": [
				"keyword",
				"constant"
			],
			"settings": {
				"foreground": "#569CD6"
			}
		},
		{
			"scope": "keyword.control",
			"settings": {
				"foreground": "#C586C0"
			}
		},
		{
			"scope": "keyword.operator",
			"settings": {
				"foreground": "#569CD6"
			}
		},
		{
			"scope":"support.class.alpine",
			"settings":{
				"foreground":"#4EC9B0"
			}
		},
		{
			"scope":"variable.alpine",
			"settings":{
				"foreground":"#4FC1FF"
			}
		},
		{
			"scope": [
				"keyword.operator.infix",
				"keyword.operator.expression",
				"keyword.operator.cast",
				"keyword.operator.sizeof",
				"keyword.operator.alignof",
				"keyword.operator.typeid",
				"keyword.operator.alignas",
				"keyword.operator.instanceof",
				"keyword.operator.logical.python",
				"keyword.operator.wordlike"
			],
			"settings": {
				"foreground": "#D4D4D4"
			}
		},
		{
			"scope": [
				"constant.character.escape"
			],
			"settings": {
				"foreground": "#D7BA7D"
			}
		},
		{
			"scope": "storage.type.alpine",
			"settings": {
				"foreground": "#569CD6"
			}
		},
		{
			"scope": [
				"support.type.record.alpine"
			],
			"settings": {
				"foreground": "#DCDCAA"
			}
		}
	],
	"tokenColors": [
		{
			"scope": "support.type",
			"settings": {
				"foreground": "#569CD6"
			}
		}
	],
	"semanticHighlighting": true,
	"semanticTokenColors": {
		"type": "#569CD6"
	}
}